libpyfoscamcgi/__init__.py
libpyfoscamcgi/foscamcgi.py
libpyfoscamcgi-0.0.9.dist-info/licenses/LICENSE
libpyfoscamcgi-0.0.9.dist-info/METADATA
libpyfoscamcgi-0.0.9.dist-info/WHEEL
libpyfoscamcgi-0.0.9.dist-info/top_level.txt
libpyfoscamcgi-0.0.9.dist-info/RECORD
