Metadata-Version: 2.4
Name: libpyfoscamcgi
Version: 0.0.9
Summary: foscam camera cgi
Home-page: https://github.com/Foscam-wangzhengyu/libfoscamcgi
Author: Foscam-wangzhengyu
Author-email: wangzhengyu@foscam.com
License: LGPLv3+
License-File: LICENSE
Requires-Dist: defusedxml
Dynamic: author
Dynamic: author-email
Dynamic: home-page
Dynamic: license
Dynamic: license-file
Dynamic: requires-dist
Dynamic: summary
